{
	"backtrace" : 1,
	"backtraceGraph" : 
	{
		"commands" : 
		[
			"add_custom_target",
			"add_dependencies",
			"add_noisepage_test",
			"add_jumbotest"
		],
		"files" : 
		[
			"CMakeLists.txt"
		],
		"nodes" : 
		[
			{
				"file" : 0
			},
			{
				"command" : 0,
				"file" : 0,
				"line" : 808,
				"parent" : 0
			},
			{
				"command" : 3,
				"file" : 0,
				"line" : 1030,
				"parent" : 0
			},
			{
				"command" : 2,
				"file" : 0,
				"line" : 1002,
				"parent" : 2
			},
			{
				"command" : 1,
				"file" : 0,
				"line" : 907,
				"parent" : 3
			},
			{
				"command" : 3,
				"file" : 0,
				"line" : 1029,
				"parent" : 0
			},
			{
				"command" : 2,
				"file" : 0,
				"line" : 997,
				"parent" : 5
			},
			{
				"command" : 1,
				"file" : 0,
				"line" : 907,
				"parent" : 6
			},
			{
				"command" : 3,
				"file" : 0,
				"line" : 1028,
				"parent" : 0
			},
			{
				"command" : 2,
				"file" : 0,
				"line" : 1002,
				"parent" : 8
			},
			{
				"command" : 1,
				"file" : 0,
				"line" : 907,
				"parent" : 9
			},
			{
				"command" : 2,
				"file" : 0,
				"line" : 997,
				"parent" : 8
			},
			{
				"command" : 1,
				"file" : 0,
				"line" : 907,
				"parent" : 11
			},
			{
				"command" : 2,
				"file" : 0,
				"line" : 997,
				"parent" : 8
			},
			{
				"command" : 1,
				"file" : 0,
				"line" : 907,
				"parent" : 13
			},
			{
				"command" : 2,
				"file" : 0,
				"line" : 997,
				"parent" : 8
			},
			{
				"command" : 1,
				"file" : 0,
				"line" : 907,
				"parent" : 15
			},
			{
				"command" : 2,
				"file" : 0,
				"line" : 997,
				"parent" : 8
			},
			{
				"command" : 1,
				"file" : 0,
				"line" : 907,
				"parent" : 17
			},
			{
				"command" : 2,
				"file" : 0,
				"line" : 997,
				"parent" : 8
			},
			{
				"command" : 1,
				"file" : 0,
				"line" : 907,
				"parent" : 19
			},
			{
				"command" : 3,
				"file" : 0,
				"line" : 1026,
				"parent" : 0
			},
			{
				"command" : 2,
				"file" : 0,
				"line" : 1002,
				"parent" : 21
			},
			{
				"command" : 1,
				"file" : 0,
				"line" : 907,
				"parent" : 22
			},
			{
				"command" : 3,
				"file" : 0,
				"line" : 1022,
				"parent" : 0
			},
			{
				"command" : 2,
				"file" : 0,
				"line" : 997,
				"parent" : 24
			},
			{
				"command" : 1,
				"file" : 0,
				"line" : 907,
				"parent" : 25
			},
			{
				"command" : 3,
				"file" : 0,
				"line" : 1019,
				"parent" : 0
			},
			{
				"command" : 2,
				"file" : 0,
				"line" : 1002,
				"parent" : 27
			},
			{
				"command" : 1,
				"file" : 0,
				"line" : 907,
				"parent" : 28
			},
			{
				"command" : 2,
				"file" : 0,
				"line" : 997,
				"parent" : 27
			},
			{
				"command" : 1,
				"file" : 0,
				"line" : 907,
				"parent" : 30
			},
			{
				"command" : 3,
				"file" : 0,
				"line" : 1020,
				"parent" : 0
			},
			{
				"command" : 2,
				"file" : 0,
				"line" : 1002,
				"parent" : 32
			},
			{
				"command" : 1,
				"file" : 0,
				"line" : 907,
				"parent" : 33
			},
			{
				"command" : 2,
				"file" : 0,
				"line" : 997,
				"parent" : 8
			},
			{
				"command" : 1,
				"file" : 0,
				"line" : 907,
				"parent" : 35
			},
			{
				"command" : 2,
				"file" : 0,
				"line" : 997,
				"parent" : 27
			},
			{
				"command" : 1,
				"file" : 0,
				"line" : 907,
				"parent" : 37
			},
			{
				"command" : 2,
				"file" : 0,
				"line" : 997,
				"parent" : 27
			},
			{
				"command" : 1,
				"file" : 0,
				"line" : 907,
				"parent" : 39
			},
			{
				"command" : 2,
				"file" : 0,
				"line" : 997,
				"parent" : 27
			},
			{
				"command" : 1,
				"file" : 0,
				"line" : 907,
				"parent" : 41
			},
			{
				"command" : 3,
				"file" : 0,
				"line" : 1018,
				"parent" : 0
			},
			{
				"command" : 2,
				"file" : 0,
				"line" : 997,
				"parent" : 43
			},
			{
				"command" : 1,
				"file" : 0,
				"line" : 907,
				"parent" : 44
			},
			{
				"command" : 3,
				"file" : 0,
				"line" : 1016,
				"parent" : 0
			},
			{
				"command" : 2,
				"file" : 0,
				"line" : 1002,
				"parent" : 46
			},
			{
				"command" : 1,
				"file" : 0,
				"line" : 907,
				"parent" : 47
			},
			{
				"command" : 2,
				"file" : 0,
				"line" : 997,
				"parent" : 27
			},
			{
				"command" : 1,
				"file" : 0,
				"line" : 907,
				"parent" : 49
			},
			{
				"command" : 3,
				"file" : 0,
				"line" : 1023,
				"parent" : 0
			},
			{
				"command" : 2,
				"file" : 0,
				"line" : 997,
				"parent" : 51
			},
			{
				"command" : 1,
				"file" : 0,
				"line" : 907,
				"parent" : 52
			},
			{
				"command" : 2,
				"file" : 0,
				"line" : 997,
				"parent" : 43
			},
			{
				"command" : 1,
				"file" : 0,
				"line" : 907,
				"parent" : 54
			},
			{
				"command" : 3,
				"file" : 0,
				"line" : 1031,
				"parent" : 0
			},
			{
				"command" : 2,
				"file" : 0,
				"line" : 1002,
				"parent" : 56
			},
			{
				"command" : 1,
				"file" : 0,
				"line" : 907,
				"parent" : 57
			},
			{
				"command" : 2,
				"file" : 0,
				"line" : 997,
				"parent" : 8
			},
			{
				"command" : 1,
				"file" : 0,
				"line" : 907,
				"parent" : 59
			},
			{
				"command" : 3,
				"file" : 0,
				"line" : 1025,
				"parent" : 0
			},
			{
				"command" : 2,
				"file" : 0,
				"line" : 1002,
				"parent" : 61
			},
			{
				"command" : 1,
				"file" : 0,
				"line" : 907,
				"parent" : 62
			},
			{
				"command" : 2,
				"file" : 0,
				"line" : 997,
				"parent" : 27
			},
			{
				"command" : 1,
				"file" : 0,
				"line" : 907,
				"parent" : 64
			},
			{
				"command" : 3,
				"file" : 0,
				"line" : 1017,
				"parent" : 0
			},
			{
				"command" : 2,
				"file" : 0,
				"line" : 997,
				"parent" : 66
			},
			{
				"command" : 1,
				"file" : 0,
				"line" : 907,
				"parent" : 67
			},
			{
				"command" : 2,
				"file" : 0,
				"line" : 1002,
				"parent" : 51
			},
			{
				"command" : 1,
				"file" : 0,
				"line" : 907,
				"parent" : 69
			},
			{
				"command" : 2,
				"file" : 0,
				"line" : 997,
				"parent" : 8
			},
			{
				"command" : 1,
				"file" : 0,
				"line" : 907,
				"parent" : 71
			},
			{
				"command" : 2,
				"file" : 0,
				"line" : 997,
				"parent" : 43
			},
			{
				"command" : 1,
				"file" : 0,
				"line" : 907,
				"parent" : 73
			},
			{
				"command" : 2,
				"file" : 0,
				"line" : 997,
				"parent" : 8
			},
			{
				"command" : 1,
				"file" : 0,
				"line" : 907,
				"parent" : 75
			},
			{
				"command" : 3,
				"file" : 0,
				"line" : 1021,
				"parent" : 0
			},
			{
				"command" : 2,
				"file" : 0,
				"line" : 997,
				"parent" : 77
			},
			{
				"command" : 1,
				"file" : 0,
				"line" : 907,
				"parent" : 78
			},
			{
				"command" : 3,
				"file" : 0,
				"line" : 1024,
				"parent" : 0
			},
			{
				"command" : 2,
				"file" : 0,
				"line" : 1002,
				"parent" : 80
			},
			{
				"command" : 1,
				"file" : 0,
				"line" : 907,
				"parent" : 81
			},
			{
				"command" : 2,
				"file" : 0,
				"line" : 1002,
				"parent" : 66
			},
			{
				"command" : 1,
				"file" : 0,
				"line" : 907,
				"parent" : 83
			},
			{
				"command" : 2,
				"file" : 0,
				"line" : 997,
				"parent" : 8
			},
			{
				"command" : 1,
				"file" : 0,
				"line" : 907,
				"parent" : 85
			},
			{
				"command" : 2,
				"file" : 0,
				"line" : 997,
				"parent" : 2
			},
			{
				"command" : 1,
				"file" : 0,
				"line" : 907,
				"parent" : 87
			},
			{
				"command" : 2,
				"file" : 0,
				"line" : 997,
				"parent" : 27
			},
			{
				"command" : 1,
				"file" : 0,
				"line" : 907,
				"parent" : 89
			},
			{
				"command" : 2,
				"file" : 0,
				"line" : 997,
				"parent" : 27
			},
			{
				"command" : 1,
				"file" : 0,
				"line" : 907,
				"parent" : 91
			},
			{
				"command" : 3,
				"file" : 0,
				"line" : 1027,
				"parent" : 0
			},
			{
				"command" : 2,
				"file" : 0,
				"line" : 1002,
				"parent" : 93
			},
			{
				"command" : 1,
				"file" : 0,
				"line" : 907,
				"parent" : 94
			},
			{
				"command" : 2,
				"file" : 0,
				"line" : 997,
				"parent" : 80
			},
			{
				"command" : 1,
				"file" : 0,
				"line" : 907,
				"parent" : 96
			},
			{
				"command" : 2,
				"file" : 0,
				"line" : 1002,
				"parent" : 43
			},
			{
				"command" : 1,
				"file" : 0,
				"line" : 907,
				"parent" : 98
			}
		]
	},
	"dependencies" : 
	[
		{
			"backtrace" : 4,
			"id" : "jumbotest_transaction_other::@6890427a1f51a3e7e1df"
		},
		{
			"backtrace" : 7,
			"id" : "jumbotest_traffic_cop_traffic_cop_test::@6890427a1f51a3e7e1df"
		},
		{
			"backtrace" : 10,
			"id" : "jumbotest_storage_other::@6890427a1f51a3e7e1df"
		},
		{
			"backtrace" : 12,
			"id" : "jumbotest_storage_tuple_access_strategy_test::@6890427a1f51a3e7e1df"
		},
		{
			"backtrace" : 14,
			"id" : "jumbotest_storage_large_garbage_collector_test::@6890427a1f51a3e7e1df"
		},
		{
			"backtrace" : 16,
			"id" : "jumbotest_storage_data_table_concurrent_test::@6890427a1f51a3e7e1df"
		},
		{
			"backtrace" : 18,
			"id" : "jumbotest_storage_data_table_test::@6890427a1f51a3e7e1df"
		},
		{
			"backtrace" : 20,
			"id" : "jumbotest_storage_block_compactor_test::@6890427a1f51a3e7e1df"
		},
		{
			"backtrace" : 23,
			"id" : "jumbotest_planner::@6890427a1f51a3e7e1df"
		},
		{
			"backtrace" : 26,
			"id" : "jumbotest_metrics_metrics_test::@6890427a1f51a3e7e1df"
		},
		{
			"backtrace" : 29,
			"id" : "jumbotest_execution_other::@6890427a1f51a3e7e1df"
		},
		{
			"backtrace" : 31,
			"id" : "jumbotest_execution_vm::@6890427a1f51a3e7e1df"
		},
		{
			"backtrace" : 34,
			"id" : "jumbotest_integration::@6890427a1f51a3e7e1df"
		},
		{
			"backtrace" : 36,
			"id" : "jumbotest_storage_log_test::@6890427a1f51a3e7e1df"
		},
		{
			"backtrace" : 38,
			"id" : "jumbotest_execution_compiler_test::@6890427a1f51a3e7e1df"
		},
		{
			"backtrace" : 40,
			"id" : "jumbotest_execution_ast::@6890427a1f51a3e7e1df"
		},
		{
			"backtrace" : 42,
			"id" : "jumbotest_execution_index_iterator_test::@6890427a1f51a3e7e1df"
		},
		{
			"backtrace" : 45,
			"id" : "jumbotest_common_rusage_monitor_test::@6890427a1f51a3e7e1df"
		},
		{
			"backtrace" : 48,
			"id" : "jumbotest_binder::@6890427a1f51a3e7e1df"
		},
		{
			"backtrace" : 50,
			"id" : "jumbotest_execution_util::@6890427a1f51a3e7e1df"
		},
		{
			"backtrace" : 53,
			"id" : "jumbotest_network_network_test::@6890427a1f51a3e7e1df"
		},
		{
			"backtrace" : 55,
			"id" : "jumbotest_common_bitmap_test::@6890427a1f51a3e7e1df"
		},
		{
			"backtrace" : 58,
			"id" : "jumbotest_type::@6890427a1f51a3e7e1df"
		},
		{
			"backtrace" : 60,
			"id" : "jumbotest_storage_block_access_controller_test::@6890427a1f51a3e7e1df"
		},
		{
			"backtrace" : 63,
			"id" : "jumbotest_parser::@6890427a1f51a3e7e1df"
		},
		{
			"backtrace" : 65,
			"id" : "jumbotest_execution_index_create_test::@6890427a1f51a3e7e1df"
		},
		{
			"backtrace" : 68,
			"id" : "jumbotest_catalog_catalog_sql_test::@6890427a1f51a3e7e1df"
		},
		{
			"backtrace" : 70,
			"id" : "jumbotest_network_other::@6890427a1f51a3e7e1df"
		},
		{
			"backtrace" : 72,
			"id" : "jumbotest_storage_hash_index_test::@6890427a1f51a3e7e1df"
		},
		{
			"backtrace" : 74,
			"id" : "jumbotest_common_concurrent_bitmap_test::@6890427a1f51a3e7e1df"
		},
		{
			"backtrace" : 76,
			"id" : "jumbotest_storage_bwtree_test::@6890427a1f51a3e7e1df"
		},
		{
			"backtrace" : 79,
			"id" : "jumbotest_messenger_messenger_test::@6890427a1f51a3e7e1df"
		},
		{
			"backtrace" : 82,
			"id" : "jumbotest_optimizer_other::@6890427a1f51a3e7e1df"
		},
		{
			"backtrace" : 84,
			"id" : "jumbotest_catalog_other::@6890427a1f51a3e7e1df"
		},
		{
			"backtrace" : 86,
			"id" : "jumbotest_storage_bwtree_index_test::@6890427a1f51a3e7e1df"
		},
		{
			"backtrace" : 88,
			"id" : "jumbotest_transaction_large_transaction_test::@6890427a1f51a3e7e1df"
		},
		{
			"backtrace" : 90,
			"id" : "jumbotest_execution_storage_interface_test::@6890427a1f51a3e7e1df"
		},
		{
			"backtrace" : 92,
			"id" : "jumbotest_execution_sql::@6890427a1f51a3e7e1df"
		},
		{
			"backtrace" : 95,
			"id" : "jumbotest_settings::@6890427a1f51a3e7e1df"
		},
		{
			"backtrace" : 97,
			"id" : "jumbotest_optimizer_hyperloglog_test::@6890427a1f51a3e7e1df"
		},
		{
			"backtrace" : 99,
			"id" : "jumbotest_common_other::@6890427a1f51a3e7e1df"
		}
	],
	"id" : "jumbotests::@6890427a1f51a3e7e1df",
	"name" : "jumbotests",
	"paths" : 
	{
		"build" : ".",
		"source" : "."
	},
	"sourceGroups" : 
	[
		{
			"name" : "",
			"sourceIndexes" : 
			[
				0
			]
		},
		{
			"name" : "CMake Rules",
			"sourceIndexes" : 
			[
				1
			]
		}
	],
	"sources" : 
	[
		{
			"backtrace" : 1,
			"isGenerated" : true,
			"path" : "cmake-build-remotedebug/CMakeFiles/jumbotests",
			"sourceGroupIndex" : 0
		},
		{
			"backtrace" : 0,
			"isGenerated" : true,
			"path" : "cmake-build-remotedebug/CMakeFiles/jumbotests.rule",
			"sourceGroupIndex" : 1
		}
	],
	"type" : "UTILITY"
}
